frozentype/__init__.py
frozentype/_frozendict.cp35-win32.pyd
frozentype/frozendict.cp35-win32.pyd
frozentype/frozendict.py
frozentype/frozenmap.cp35-win32.pyd
frozentype/frozenmap.py
frozentype/test/__init__.py
frozentype/test/test_frozendict.py
frozentype-0.6.0.1.dist-info/LICENSE.txt
frozentype-0.6.0.1.dist-info/METADATA
frozentype-0.6.0.1.dist-info/WHEEL
frozentype-0.6.0.1.dist-info/top_level.txt
frozentype-0.6.0.1.dist-info/RECORD
