Metadata-Version: 2.1
Name: frozentype
Version: 0.6.0.1
Summary: Package frozentype provide some frozen python types (frozendict (C based) and frozenmap (Cython based))
Home-page: http://intellimath.bitbucket.org/frozentype
Author: Zaur Shibzukhov
Author-email: szport@gmail.com
License: MIT License
Download-URL: https://bitbucket.org/intellimath/frozentype
Keywords: frozen type,frozen mapping,immutable mapping,frozen dict,immutable dict
Platform: Linux
Platform: Mac OS X
Platform: Windows
Classifier: Development Status :: 4 - Beta
Classifier: Intended Audience :: Developers
Classifier: Intended Audience :: Information Technology
Classifier: License :: OSI Approved :: MIT License
Classifier: Programming Language :: Python :: 2
Classifier: Programming Language :: Python :: 2.7
Classifier: Programming Language :: Python :: 3
Classifier: Programming Language :: Python :: 3.4
Classifier: Programming Language :: Python :: 3.5
Classifier: Programming Language :: Python :: 3.6
Classifier: Programming Language :: Python :: 3.7
Classifier: Operating System :: OS Independent
Classifier: Topic :: Software Development :: Libraries :: Python Modules
